{"pf_url": "https://www.poetryfoundation.org/poets/brenda-coultas", "name": "Brenda Coultas", "yob": null, "yod": null, "image": "https://media.poetryfoundation.org/uploads/media/default/0001/17/a79d6e74e261e312d5701c0c6b4c6379cd65c1cd.jpeg", "bio": "\nBrenda Coultas\u00a0is the author of the poetry collections\u00a0A Journal of Places (online, Metambesen Press, 2015), The Tatters (Wesleyan University Press, 2014), The Marvelous Bones of Time\u00a0(Coffee House Press, 2007), and\u00a0A Handmade Museum (Coffee House Press, 2003). Her poetry can be found in anthologies, including\u00a0Readings in Contemporary Poetry: An Anthology (2017),\u00a0What is Poetry (Just Kidding, I Know You Know):\u00a0Interviews from the Poetry Project Newsletter (1983-2009) (2017), and\u00a0Symmetries: Three Years of Art and Poetry at Dominique Levy (2017).\n", "attrs": {}}