{"pf_url": "https://www.poetryfoundation.org/poets/angelina-weld-grimke", "name": "Angelina Weld Grimk\u00e9", "yob": "1880", "yod": "1958", "image": null, "bio": "\nBorn in Boston, poet and playwright Angelina Weld Grimk\u00e9 was named after her great-aunt, the abolitionist and suffragist Angelina Grimk\u00e9 Weld. Grimk\u00e9 earned a degree from the Boston Normal School of Gymnastics in physical education. She is the author of important poems on love and race, including \u201cEl Beso,\u201d \u201cDawn,\u201d \u201cBeware Lest He Awakes,\u201d and \u201cThe Black Finger.\u201d Her poems have been anthologized in Negro Poets and Their Poems (1923), The Poetry of the Negro (1949, edited by Langston Hughes), and Caroling Dusk (1927, edited by Countee Cullen).\r\n\u00a0\r\nAfter graduation, Grimk\u00e9 taught physical education and English at high schools in Washington, DC. When her father died in 1930, she moved to New York City, where she lived until her death.\n", "attrs": {"Region:": ["U.S., Mid-Atlantic"], "School/Period:": ["Harlem Renaissance"]}}