{"pf_url": "https://www.poetryfoundation.org/poets/brent-cunningham", "name": "Brent Cunningham", "yob": null, "yod": null, "image": null, "bio": "\nBrent Cunningham is a writer, publisher and visual artist currently living in Oakland with his wife and daughter. His books of poetry include\u00a0Bird & Forest\u00a0(2005) and \u00a0Journey to the Sun (2012). He and Neil Alger founded Hooke Press, a chapbook press dedicated to\u00a0publishing short runs of poetry, criticism, theory, writing and ephemera. Brent has worked for Small Press Distribution since 1999.\n", "attrs": {"Region:": ["U.S., Western"]}}