{"pf_url": "https://www.poetryfoundation.org/poets/francine-sterle", "name": "Francine Sterle", "yob": null, "yod": null, "image": "https://media.poetryfoundation.org/uploads/media/default/0001/02/6992382c940dfba59c014f762d55fd3e4bfc2159.jpeg", "bio": "\nFrancine Sterle is the author of What Thread? (Red Dragonfly Press, 2015), winner of the David Martinson\u2014Meadowhawk Prize;\u00a0Nude in Winter (Tupelo Press, 2007);\u00a0Every Bird is One Bird (Tupelo Press, 2001), winner of the\u00a0Editor\u2019s Prize;\u00a0and The White Bridge (Poetry Harbor, 1999). Her poems have appeared in such journals as Ploughshares, the North American Review, Poetry International, and Nimrod, and her poems have been anthologized in Written on Water, Letters to the World, To Sing Along the Way, The Cancer Poetry Project, and 33 Minnesota Poets.Sterle's awards include ten Pushcart Prize nominations, a Los Angeles Book of the Year nomination, a Loft-McKnight Foundation Award, a Jerome Foundation Travel and Study Grant, and a Lake Superior Contemporary Writers Award; she has received a Career Initiative Grant from the Arrowhead Regional Arts Council as well as both a Fellowship Grant and a Career Opportunity Grant from the Minnesota State Arts Board. She has served residencies at the Anderson Center for Interdisciplinary Studies, the Leighton Studios at the Banff Centre for the Arts, and the Blacklock Nature Sanctuary. \u00a0\n", "attrs": {}}